vdfparse/VDFParse.py
vdfparse/__init__.py
vdfparse-1.0.0.dist-info/licenses/LICENSE
vdfparse-1.0.0.dist-info/METADATA
vdfparse-1.0.0.dist-info/WHEEL
vdfparse-1.0.0.dist-info/top_level.txt
vdfparse-1.0.0.dist-info/RECORD
